play_num_pkg/__init__.py
play_num_pkg/play_num_pkg.py
play_num_pkg-0.0.1.dist-info/METADATA
play_num_pkg-0.0.1.dist-info/WHEEL
play_num_pkg-0.0.1.dist-info/licenses/LICENSE
play_num_pkg-0.0.1.dist-info/RECORD
